django_base_publications/__init__.py
django_base_publications/admin.py
django_base_publications/apps.py
django_base_publications/locale/ru/LC_MESSAGES/django.mo
django_base_publications/locale/ru/LC_MESSAGES/django.po
django_base_publications/migrations/__init__.py
django_base_publications/models/__init__.py
django_base_publications/models/managers.py
django_base_publications/models/publications.py
django_base_publications/models/statuses.py
django_base_publications/rss.py
django_base_publications/settings.py
django_base_publications/sitemaps.py
django_base_publications/tests.py
django_base_publications/utils.py
django_base_publications/views.py
django_base_publications-0.0.6.dist-info/WHEEL
django_base_publications-0.0.6.dist-info/METADATA
django_base_publications-0.0.6.dist-info/RECORD
